MANIFEST.in
README.md
chipper.py
setup.py
chipper.egg-info/PKG-INFO
chipper.egg-info/SOURCES.txt
chipper.egg-info/dependency_links.txt
chipper.egg-info/requires.txt
chipper.egg-info/top_level.txt