Metadata-Version: 1.1
Name: chipper
Version: 0.1
Summary: Refreshingly simple declarative logging that utilizes arbitrary tag sinks instead of traditional level handling
Home-page: https://github.com/dustinlacewell/chipper
Author: Dustin Lacewell
Author-email: dlacewell@gmail.com
License: UNKNOWN
Platform: UNKNOWN
Provides: chipper
